{
	"client": "./client",
	"svr": "./server",
	"appid": "wx535154afcda10e53",
	"projectname": "wafer",
	"setting": {
		"newFeature": true
	},
	"libVersion": "1.9.9",
	"condition": {
		"search": {
			"current": -1,
			"list": []
		},
		"conversation": {
			"current": -1,
			"list": []
		},
		"plugin": {
			"current": -1,
			"list": []
		},
		"game": {
			"list": []
		},
		"miniprogram": {
			"current": -1,
			"list": [
				{
					"id": 0,
					"name": "个人中心",
					"pathName": "pages/myinfo/index",
					"query": "id=10"
				},
				{
					"id": 1,
					"name": "详情",
					"pathName": "pages/detail/index",
					"query": "id=25"
				},
				{
					"id": 2,
					"name": "new",
					"pathName": "pages/detail/report/index",
					"query": "id=28"
				},
				{
					"id": -1,
					"name": "数据",
					"pathName": "pages/detail/building/index",
					"query": "id=10&building=18"
				}
			]
		}
	}
}